clientsubnetoption.py
clientsubnetoption-2.1.1.dist-info/LICENSE
clientsubnetoption-2.1.1.dist-info/METADATA
clientsubnetoption-2.1.1.dist-info/WHEEL
clientsubnetoption-2.1.1.dist-info/top_level.txt
clientsubnetoption-2.1.1.dist-info/RECORD
