Metadata-Version: 2.1
Name: clientsubnetoption
Version: 2.1.1
Summary: EDNS Client Subnet option support for dnspython
Home-page: https://github.com/opendns/dnspython-clientsubnetoption
Maintainer: Brian Hartvigsen
Maintainer-email: bhartvigsen@opendns.com
License: BSD
Platform: UNKNOWN
Classifier: Development Status :: 5 - Production/Stable
Classifier: Programming Language :: Python :: 2
Classifier: Programming Language :: Python :: 2.7
Classifier: Programming Language :: Python :: 3
Requires-Dist: dnspython
